[
{"fecha_crawl": "2019-04-29 18:32:55", "perc_descuento": 0.2500078127441483, "precio_original": 319990, "precio_descuento": 239990, "url": "https://www.piranha.cl/kit-base/68/kit-tesla-60-t180w-completo.html"}
]
[
{"fecha_crawl": "2019-04-30 10:07:05", "perc_descuento": 0.2500078127441483, "precio_original": 319990, "precio_descuento": 239990, "url": "https://www.piranha.cl/kit-base/68/kit-tesla-60-t180w-completo.html"}
][
{"fecha_crawl": "2019-05-06 10:17:31", "perc_descuento": 0.2500078127441483, "precio_original": 319990, "precio_descuento": 239990, "url": "https://www.piranha.cl/kit-base/68/kit-tesla-60-t180w-completo.html"}
][
{"fecha_crawl": "2019-05-15 12:32:28", "perc_descuento": 0.30000000000000004, "precio_original": 319990, "precio_descuento": 223993, "url": "https://www.piranha.cl/kit-base/68/kit-tesla-60-t180w-completo.html"}
]